cust_logger/__init__.py
cust_logger/custom_logger.py
cust_logger-3.2.0.dist-info/METADATA
cust_logger-3.2.0.dist-info/WHEEL
cust_logger-3.2.0.dist-info/top_level.txt
cust_logger-3.2.0.dist-info/RECORD
